[
    {
        "start": "0.2",
        "end": "4.8"
    },
    {
        "start": "5.3",
        "end": "9.7"
    },
    {
        "start": "10.3",
        "end": "14.9"
    },
    {
        "start": "15.5",
        "end": "20"
    },
    {
        "start": "20.4",
        "end": "24.9"
    },
    {
        "start": "25.5",
        "end": "30"
    },
    {
        "start": "31",
        "end": "35.3"
    },
    {
        "start": "36.4",
        "end": "41.7"
    },
    {
        "start": "42.3",
        "end": "47.3"
    },
    {
        "start": "47.8",
        "end": "52.2"
    },
    {
        "start": "53.1",
        "end": "58.1"
    },
    {
        "start": "58.5",
        "end": "63.1"
    },
    {
        "start": "63.8",
        "end": "69.7"
    },
    {
        "start": "69.9",
        "end": "75.2"
    },
    {
        "start": "75.6",
        "end": "80.2"
    },
    {
        "start": "81.2",
        "end": "90.2"
    }
]