[
    {
        "start": "0.3",
        "end": "4.9"
    },
    {
        "start": "5.5",
        "end": "10.3"
    },
    {
        "start": "11",
        "end": "15.8"
    },
    {
        "start": "16.3",
        "end": "20.9"
    },
    {
        "start": "21.9",
        "end": "26.8"
    },
    {
        "start": "27.5",
        "end": "32.7"
    },
    {
        "start": "33.6",
        "end": "38.9"
    },
    {
        "start": "39.3",
        "end": "44.2"
    },
    {
        "start": "45",
        "end": "50.7"
    },
    {
        "start": "51",
        "end": "56.5"
    },
    {
        "start": "56.7",
        "end": "61.6"
    },
    {
        "start": "62.3",
        "end": "67.1"
    },
    {
        "start": "68.1",
        "end": "74.2"
    },
    {
        "start": "74.6",
        "end": "79.6"
    },
    {
        "start": "81",
        "end": "87"
    },
    {
        "start": "87.8",
        "end": "97.9"
    }
]